Workbook
Name SalesData: SalesDataa[]
Name Slicer_Customer_Type: #N/A
Name Slicer_Region: #N/A
Name SMALLTABLE: SMALL_TABLE[]

Sheet SalesDataa
A1: Customer Name | B1: Amount | C1: Transaction Type | D1: Amount | E1: Tax | F1: Net Amount | G1: Region | H1: Transaction Date | I1: Sales Rep | J1: Collection Date | K1: Remaining Days | L1: Customer Name | M1: Region | N1: Net Amount | O1: Customer Type | P1: Sales Percentage
A2: Ahmed Mamdouh | B2: 15000 | C2: Invoice | D2: 15000 | E2: =$D$2*0.14 -> 2100 | F2: =SalesDataa[[#This Row],[Amount ]]-SalesDataa[[#This Row],[Tax]] -> 12900 | G2: Cairo | H2: 44213 | I2: Sayed | J2: 44255 | K2: =SalesDataa[[#This Row],[Collection Date]]-SalesDataa[[#This Row],[Transaction Date]] -> 42 | L2: Ahmed Mamdouh | M2: =VLOOKUP(L2:L11,database!$A$1:$B$19,2,FALSE) -> Cairo | N2: =SUMIFS($F$2:$F$19,SalesDataa[Customer Name],L2,SalesDataa[Transaction Type],"Invoice")-SUMIFS($F$2:$F$19,SalesDataa[Customer Name],L2,SalesDataa[Transaction Type],"Return")-SUMIFS($F$2:$F$19,SalesDataa[Customer Name],L2,SalesDataa[Transaction Type],"Discount") -> 14000 | O2: =IF(N2>10000,"Key Customer","Regular Customer") -> Key Customer | P2: =N2/SUM($N$2:$N$11) -> 0.093770931
A3: Ahmed Mamdouh | B3: 1000 | C3: Return | D3: 1000 | E3: =$D$2*0.14 -> 2100 | F3: =SalesDataa[[#This Row],[Amount ]]-SalesDataa[[#This Row],[Tax]] -> -1100 | G3: Cairo | H3: 44222 | I3: Sayed | J3: 44255 | K3: =SalesDataa[[#This Row],[Collection Date]]-SalesDataa[[#This Row],[Transaction Date]] -> 33 | L3: Asaad Sherif | M3: =VLOOKUP(L3:L12,database!$A$1:$B$19,2,FALSE) -> Beheira | N3: =SUMIFS($F$2:$F$19,SalesDataa[Customer Name],L3,SalesDataa[Transaction Type],"Invoice")-SUMIFS($F$2:$F$19,SalesDataa[Customer Name],L3,SalesDataa[Transaction Type],"Return")-SUMIFS($F$2:$F$19,SalesDataa[Customer Name],L3,SalesDataa[Transaction Type],"Discount") -> 900 | O3: =IF(N3>10000,"Key Customer","Regular Customer") -> Regular Customer | P3: =N3/SUM($N$2:$N$11) -> 0.0060281313
A4: Asaad Sherif | B4: 3000 | C4: Invoice | D4: 3000 | E4: =$D$2*0.14 -> 2100 | F4: =SalesDataa[[#This Row],[Amount ]]-SalesDataa[[#This Row],[Tax]] -> 900 | G4: Beheira | H4: 44218 | I4: Mamd | J4: 44255 | K4: =SalesDataa[[#This Row],[Collection Date]]-SalesDataa[[#This Row],[Transaction Date]] -> 37 | L4: Ashraf Mahmoud | M4: =VLOOKUP(L4:L13,database!$A$1:$B$19,2,FALSE) -> Cairo | N4: =SUMIFS($F$2:$F$19,SalesDataa[Customer Name],L4,SalesDataa[Transaction Type],"Invoice")-SUMIFS($F$2:$F$19,SalesDataa[Customer Name],L4,SalesDataa[Transaction Type],"Return")-SUMIFS($F$2:$F$19,SalesDataa[Customer Name],L4,SalesDataa[Transaction Type],"Discount") -> 1900 | O4: =IF(N4>10000,"Key Customer","Regular Customer") -> Regular Customer | P4: =N4/SUM($N$2:$N$11) -> 0.012726055
A5: Ashraf Mahmoud | B5: 4000 | C5: Invoice | D5: 4000 | E5: =$D$2*0.14 -> 2100 | F5: =SalesDataa[[#This Row],[Amount ]]-SalesDataa[[#This Row],[Tax]] -> 1900 | G5: Cairo | H5: 44216 | I5: Nour | J5: 44255 | K5: =SalesDataa[[#This Row],[Collection Date]]-SalesDataa[[#This Row],[Transaction Date]] -> 39 | L5: Ayman Sadeq | M5: =VLOOKUP(L5:L14,database!$A$1:$B$19,2,FALSE) -> Mansoura | N5: =SUMIFS($F$2:$F$19,SalesDataa[Customer Name],L5,SalesDataa[Transaction Type],"Invoice")-SUMIFS($F$2:$F$19,SalesDataa[Customer Name],L5,SalesDataa[Transaction Type],"Return")-SUMIFS($F$2:$F$19,SalesDataa[Customer Name],L5,SalesDataa[Transaction Type],"Discount") -> 6800 | O5: =IF(N5>10000,"Key Customer","Regular Customer") -> Regular Customer | P5: =N5/SUM($N$2:$N$11) -> 0.045545881
A6: Ayman Sadeq | B6: 5000 | C6: Invoice | D6: 5000 | E6: =$D$2*0.14 -> 2100 | F6: =SalesDataa[[#This Row],[Amount ]]-SalesDataa[[#This Row],[Tax]] -> 2900 | G6: Mansoura | H6: 44212 | I6: Nour | J6: 44255 | K6: =SalesDataa[[#This Row],[Collection Date]]-SalesDataa[[#This Row],[Transaction Date]] -> 43 | L6: Sara El-Shafei | M6: =VLOOKUP(L6:L15,database!$A$1:$B$19,2,FALSE) -> Sharqia | N6: =SUMIFS($F$2:$F$19,SalesDataa[Customer Name],L6,SalesDataa[Transaction Type],"Invoice")-SUMIFS($F$2:$F$19,SalesDataa[Customer Name],L6,SalesDataa[Transaction Type],"Return")-SUMIFS($F$2:$F$19,SalesDataa[Customer Name],L6,SalesDataa[Transaction Type],"Discount") -> 13900 | O6: =IF(N6>10000,"Key Customer","Regular Customer") -> Key Customer | P6: =N6/SUM($N$2:$N$11) -> 0.093101139
A7: Ayman Sadeq | B7: 2000 | C7: Invoice | D7: 2000 | E7: =$D$2*0.14 -> 2100 | F7: =SalesDataa[[#This Row],[Amount ]]-SalesDataa[[#This Row],[Tax]] -> -100 | G7: Giza | H7: 44217 | I7: Sayed | J7: 44255 | K7: =SalesDataa[[#This Row],[Collection Date]]-SalesDataa[[#This Row],[Transaction Date]] -> 38 | L7: Sayed Afifi | M7: =VLOOKUP(L7:L16,database!$A$1:$B$19,2,FALSE) -> Minya | N7: =SUMIFS($F$2:$F$19,SalesDataa[Customer Name],L7,SalesDataa[Transaction Type],"Invoice")-SUMIFS($F$2:$F$19,SalesDataa[Customer Name],L7,SalesDataa[Transaction Type],"Return")-SUMIFS($F$2:$F$19,SalesDataa[Customer Name],L7,SalesDataa[Transaction Type],"Discount") -> 67900 | O7: =IF(N7>10000,"Key Customer","Regular Customer") -> Key Customer | P7: =N7/SUM($N$2:$N$11) -> 0.45478902
A8: Ayman Sadeq | B8: 1000 | C8: Return | D8: 1000 | E8: =$D$2*0.14 -> 2100 | F8: =SalesDataa[[#This Row],[Amount ]]-SalesDataa[[#This Row],[Tax]] -> -1100 | G8: Mansoura | H8: 44225 | I8: Nour | J8: 44255 | K8: =SalesDataa[[#This Row],[Collection Date]]-SalesDataa[[#This Row],[Transaction Date]] -> 30 | L8: Mortada El-Mesiri | M8: =VLOOKUP(L8:L17,database!$A$1:$B$19,2,FALSE) -> Mansoura | N8: =SUMIFS($F$2:$F$19,SalesDataa[Customer Name],L8,SalesDataa[Transaction Type],"Invoice")-SUMIFS($F$2:$F$19,SalesDataa[Customer Name],L8,SalesDataa[Transaction Type],"Return")-SUMIFS($F$2:$F$19,SalesDataa[Customer Name],L8,SalesDataa[Transaction Type],"Discount") -> 6900 | O8: =IF(N8>10000,"Key Customer","Regular Customer") -> Regular Customer | P8: =N8/SUM($N$2:$N$11) -> 0.046215673
A9: Ayman Sadeq | B9: 5000 | C9: Invoice | D9: 5000 | E9: =$D$2*0.14 -> 2100 | F9: =SalesDataa[[#This Row],[Amount ]]-SalesDataa[[#This Row],[Tax]] -> 2900 | G9: Mansoura | H9: 44227 | I9: Mohamed | J9: 44255 | K9: =SalesDataa[[#This Row],[Collection Date]]-SalesDataa[[#This Row],[Transaction Date]] -> 28 | L9: Maryam Mahmoud | M9: =VLOOKUP(L9:L18,database!$A$1:$B$19,2,FALSE) -> Aswan | N9: =SUMIFS($F$2:$F$19,SalesDataa[Customer Name],L9,SalesDataa[Transaction Type],"Invoice")-SUMIFS($F$2:$F$19,SalesDataa[Customer Name],L9,SalesDataa[Transaction Type],"Return")-SUMIFS($F$2:$F$19,SalesDataa[Customer Name],L9,SalesDataa[Transaction Type],"Discount") -> 25900 | O9: =IF(N9>10000,"Key Customer","Regular Customer") -> Key Customer | P9: =N9/SUM($N$2:$N$11) -> 0.17347622
A10: Sara El-Shafei | B10: 16000 | C10: Invoice | D10: 16000 | E10: =$D$2*0.14 -> 2100 | F10: =SalesDataa[[#This Row],[Amount ]]-SalesDataa[[#This Row],[Tax]] -> 13900 | G10: Sharqia | H10: 44220 | I10: Nour | J10: 44255 | K10: =SalesDataa[[#This Row],[Collection Date]]-SalesDataa[[#This Row],[Transaction Date]] -> 35 | L10: Mostafa Yousry | M10: =VLOOKUP(L10:L19,database!$A$1:$B$19,2,FALSE) -> Beheira | N10: =SUMIFS($F$2:$F$19,SalesDataa[Customer Name],L10,SalesDataa[Transaction Type],"Invoice")-SUMIFS($F$2:$F$19,SalesDataa[Customer Name],L10,SalesDataa[Transaction Type],"Return")-SUMIFS($F$2:$F$19,SalesDataa[Customer Name],L10,SalesDataa[Transaction Type],"Discount") -> 3300 | O10: =IF(N10>10000,"Key Customer","Regular Customer") -> Regular Customer | P10: =N10/SUM($N$2:$N$11) -> 0.022103148
A11: Sayed Afifi | B11: 70000 | C11: Invoice | D11: 70000 | E11: =$D$2*0.14 -> 2100 | F11: =SalesDataa[[#This Row],[Amount ]]-SalesDataa[[#This Row],[Tax]] -> 67900 | G11: Minya | H11: 44215 | I11: Mostafa | J11: 44255 | K11: =SalesDataa[[#This Row],[Collection Date]]-SalesDataa[[#This Row],[Transaction Date]] -> 40 | L11: Hisham Fathy | M11: =VLOOKUP(L11:L20,database!$A$1:$B$19,2,FALSE) -> Giza | N11: =SUMIFS($F$2:$F$19,SalesDataa[Customer Name],L11,SalesDataa[Transaction Type],"Invoice")-SUMIFS($F$2:$F$19,SalesDataa[Customer Name],L11,SalesDataa[Transaction Type],"Return")-SUMIFS($F$2:$F$19,SalesDataa[Customer Name],L11,SalesDataa[Transaction Type],"Discount") -> 7800 | O11: =IF(N11>10000,"Key Customer","Regular Customer") -> Regular Customer | P11: =N11/SUM($N$2:$N$11) -> 0.052243804
A12: Mortada El-Mesiri | B12: 9000 | C12: Invoice | D12: 9000 | E12: =$D$2*0.14 -> 2100 | F12: =SalesDataa[[#This Row],[Amount ]]-SalesDataa[[#This Row],[Tax]] -> 6900 | G12: Mansoura | H12: 44219 | I12: Mostafa | J12: 44255 | K12: =SalesDataa[[#This Row],[Collection Date]]-SalesDataa[[#This Row],[Transaction Date]] -> 36
A13: Maryam Mahmoud | B13: 20000 | C13: Invoice | D13: 20000 | E13: =$D$2*0.14 -> 2100 | F13: =SalesDataa[[#This Row],[Amount ]]-SalesDataa[[#This Row],[Tax]] -> 17900 | G13: Aswan | H13: 44214 | I13: Mohamed | J13: 44255 | K13: =SalesDataa[[#This Row],[Collection Date]]-SalesDataa[[#This Row],[Transaction Date]] -> 41
A14: Maryam Mahmoud | B14: 10000 | C14: Invoice | D14: 10000 | E14: =$D$2*0.14 -> 2100 | F14: =SalesDataa[[#This Row],[Amount ]]-SalesDataa[[#This Row],[Tax]] -> 7900 | G14: Aswan | H14: 44221 | I14: Sayed | J14: 44255 | K14: =SalesDataa[[#This Row],[Collection Date]]-SalesDataa[[#This Row],[Transaction Date]] -> 34
A15: Maryam Mahmoud | B15: 2000 | C15: Return | D15: 2000 | E15: =$D$2*0.14 -> 2100 | F15: =SalesDataa[[#This Row],[Amount ]]-SalesDataa[[#This Row],[Tax]] -> -100 | G15: Sharqia | H15: 44226 | I15: Mohamed | J15: 44255 | K15: =SalesDataa[[#This Row],[Collection Date]]-SalesDataa[[#This Row],[Transaction Date]] -> 29
A16: Mostafa Yousry | B16: 7000 | C16: Invoice | D16: 7000 | E16: =$D$2*0.14 -> 2100 | F16: =SalesDataa[[#This Row],[Amount ]]-SalesDataa[[#This Row],[Tax]] -> 4900 | G16: Beheira | H16: 44211 | I16: Mostafa | J16: 44255 | K16: =SalesDataa[[#This Row],[Collection Date]]-SalesDataa[[#This Row],[Transaction Date]] -> 44
A17: Mostafa Yousry | B17: 500 | C17: Discount | D17: 500 | E17: =$D$2*0.14 -> 2100 | F17: =-(SalesDataa[[#This Row],[Amount ]]-SalesDataa[[#This Row],[Tax]]) -> 1600 | G17: Beheira | H17: 44224 | I17: Mostafa | J17: 44255 | K17: =SalesDataa[[#This Row],[Collection Date]]-SalesDataa[[#This Row],[Transaction Date]] -> 31
A18: Hisham Fathy | B18: 10000 | C18: Invoice | D18: 10000 | E18: =$D$2*0.14 -> 2100 | F18: =SalesDataa[[#This Row],[Amount ]]-SalesDataa[[#This Row],[Tax]] -> 7900 | G18: Giza | H18: 44210 | I18: Mohamed | J18: 44255 | K18: =SalesDataa[[#This Row],[Collection Date]]-SalesDataa[[#This Row],[Transaction Date]] -> 45
A19: Hisham Fathy | B19: 2000 | C19: Discount | D19: 2000 | E19: =$D$2*0.14 -> 2100 | F19: =-(SalesDataa[[#This Row],[Amount ]]-SalesDataa[[#This Row],[Tax]]) -> 100 | G19: Giza | H19: 44223 | I19: Mohamed | J19: 44255 | K19: =SalesDataa[[#This Row],[Collection Date]]-SalesDataa[[#This Row],[Transaction Date]] -> 32
D20: =SUMIFS(D2:D19,SalesDataa[Transaction Type],"Invoice",SalesDataa[Region],"Cairo") -> 19000 | E20: =SUM(SalesDataa[Tax]) -> 37800 | F20: =SUM(SalesDataa[Net Amount]) -> 148100 | K20: =SUM(SalesDataa[Remaining Days]) -> 657

Sheet database
A1: Customer Name | B1: Region
A2: Ahmed Mamdouh | B2: Cairo
A3: Ahmed Mamdouh | B3: Cairo
A4: Asaad Sherif | B4: Beheira
A5: Ashraf Mahmoud | B5: Cairo
A6: Ayman Sadeq | B6: Mansoura
A7: Ayman Sadeq | B7: Giza
A8: Ayman Sadeq | B8: Mansoura
A9: Ayman Sadeq | B9: Mansoura
A10: Sara El-Shafei | B10: Sharqia
A11: Sayed Afifi | B11: Minya
A12: Mortada El-Mesiri | B12: Mansoura
... A19: Hisham Fathy | B19: Giza

Sheet Sales by Customer
A3: Row Labels | B3: Sum of Net Amount
A4: Ahmed Mamdouh | B4: 11800
A5: Asaad Sherif | B5: 900
A6: Ashraf Mahmoud | B6: 1900
A7: Ayman Sadeq | B7: 4600
A8: Hisham Fathy | B8: 8000
A9: Maryam Mahmoud | B9: 25700
A10: Mortada El-Mesiri | B10: 6900
A11: Mostafa Yousry | B11: 6500
A12: Sara El-Shafei | B12: 13900
A13: Sayed Afifi | B13: 67900
A14: Grand Total | B14: 148100

Sheet Sales Trend
A3: Row Labels | B3: Sales Trend
A4: 44210 | B4: 10000
A5: 44211 | B5: 7000
A6: 44212 | B6: 5000
A7: 44213 | B7: 15000
A8: 44214 | B8: 20000
A9: 44215 | B9: 70000
A10: 44216 | B10: 4000
A11: 44217 | B11: 2000
A12: 44218 | B12: 3000
A13: 44219 | B13: 9000
A14: 44220 | B14: 16000
A15: 44221 | B15: 10000
... A21: 44227 | B21: 5000
A22: Grand Total | B22: 182500

Sheet Sales by Region
A3: Row Labels | B3: Sum of Net Amount
A4: Aswan | B4: 25800
A5: Beheira | B5: 7400
A6: Cairo | B6: 13700
A7: Giza | B7: 7900
A8: Mansoura | B8: 11600
A9: Minya | B9: 67900
A10: Sharqia | B10: 13800
A11: Grand Total | B11: 148100

Sheet Sales by Customer Type
A3: Row Labels | B3: Sum of Net Amount
A4: Key Customer | B4: 121700
A5: Regular Customer | B5: 27600
A6: Grand Total | B6: 149300

Sheet Sales by Sales Rep
A3: Row Labels | B3: Sum of Net Amount
A4: Mamd | B4: 900
A5: Mohamed | B5: 28700
A6: Mostafa | B6: 81300
A7: Nour | B7: 17600
A8: Sayed | B8: 19600
A9: Grand Total | B9: 148100

Sheet لوحة التحكم
E3: Sales Data
